[
  {
    "imageLinks": [
      "image/มะเขือราชินีอบแห้ง.jpg",
      "image/มะเขือราชินีอบแห้ง3.jpg",
      "image/มะเขือราชินีอบแห้ง7.jpg"
    ],
    "productDetails": {
      "productName": "มะเขือราชินีอบแห้ง",
      "origin": "กลุ่มมะเขือเทศราชินีดำเนินงานจัดตั้งเมื่อปีพ.ศ. 2549...",
      "productionLocation": "65 หมู่ที่ 5 ตำบลดอนตูม อำเภอบางเลน จังหวัดนครปฐม"
    }
  },
  {
    "imageLinks": [
      "image/เบญจรงค์ประยุกต์.jpg",
      "image/เบญจรงค์ประยุกต์2.jpg",
      "image/เบญจรงค์ประยุกต์3.jpg"
    ],
    "productDetails": {
      "productName": "มะเขือราชินีอบแห้ง",
      "origin": "กลุ่มมะเขือเทศราชินีดำเนินงานจัดตั้งเมื่อปีพ.ศ. 2549...",
      "productionLocation": "65 หมู่ที่ 5 ตำบลดอนตูม อำเภอบางเลน จังหวัดนครปฐม"
    }
  },
  {
    "imageLinks": [
      "image/ขนมเปี๊ยะกุหลาบ1.jpg",
      "image/ขนมเปี๊ยะกุหลาบ2.jpg",
      "image/ขนมเปี๊ยะกุหลาบ3.jpg"
    ],
    "productDetails": {
      "productName": "ขนมเปี๊ยะกุหลาบ",
      "origin": "กลุ่มผลิตขนมทุ่งบัว เริ่มจัดตั้งกลุ่มขึ้นเมื่อ ปี พ.ศ.2541 สมาชิกเริ่มแรก จำนวน 5 คน จนมาถึงปัจจุบัน มีสมาชิก 26 คน มีการปันผลให้กับสมาชิกทุสิ้นปี สมาชิกอยู่ในตำบลทุ่งบัว ยามว่างจากงานในไร่ จะมาร่วมกันทำขนม จะเปลี่ยนมาทำรายได้ ชั่วโมงละ 15 บาท มีการระดมหุ้นจนปัจจุบันกลุ่มได้เกิดความเข้มแข็ง",
      "productionLocation": "สถานที่ผลิต 51 หมู่ที่ 1 ตำบลทุ่งบัว อำเภอกำแพงแสน  จังหวัดนครปฐม"
    }
  }
]
